{"id":"pl-pep-beben-marcin-2xppdyaqdcwebbdsvm8atal1zok","caption":"Bęben Marcin","schema":"Person","properties":{"name":["Bęben Marcin"],"sourceUrl":["https://www.kielce.uw.gov.pl/pl/urzad/dyrektor-generalny/6363,Dyrektor-Generalny.html"],"firstName":["Marcin"],"lastName":["Bęben"],"topics":["role.pep"],"position":["Dyrektor Generalny Urzędu - świętokrzyski"],"status":["Domestic Politically Exposed Person"]},"datasets":["pl_pep"]}
{"id":"pl-pep-bodziony-durych-angelika-2xppe0iswteeknjydq532wbwrxe","caption":"Bodziony-Durych Angelika","schema":"Person","properties":{"name":["Bodziony-Durych Angelika"],"sourceUrl":["https://bip.malopolska.pl/muw,m,5751,dyrektor-generalny-urzedu.html"],"firstName":["Angelika"],"lastName":["Bodziony-Durych"],"topics":["role.pep"],"position":["Dyrektor Generalny Urzędu - małopolski"],"status":["Domestic Politically Exposed Person"]},"datasets":["pl_pep"]}
{"id":"pl-pep-grula-agata-1977-11-20","caption":"Grula Agata","schema":"Person","properties":{"name":["Grula Agata"],"sourceUrl":["https://www.gov.pl/web/uw-lubelski/agata-grula"],"firstName":["Agata"],"lastName":["Grula"],"birthDate":["1977-11-20"],"topics":["role.pep"],"position":["Dyrektor Generalny Urzędu - lubelski"],"status":["Domestic Politically Exposed Person"]},"datasets":["pl_pep"]}
{"id":"pl-pep-hasiewicz-malgorzata-2xppdy0yhc0w3gtr9abvrjngscg","caption":"Hasiewicz Małgorzata","schema":"Person","properties":{"name":["Hasiewicz Małgorzata"],"sourceUrl":["https://www.duw.pl/pl/urzad/dyrektor-generalny/11711,DYREKTOR-GENERALNY.html"],"firstName":["Małgorzata"],"lastName":["Hasiewicz"],"topics":["role.pep"],"position":["Dyrektor Generalny Urzędu - dolnośląski"],"status":["Domestic Politically Exposed Person"]},"datasets":["pl_pep"]}
{"id":"pl-pep-kowalik-gesiak-jolanta-2xppe0y1tw89g3ue6e1pi4ohmeo","caption":"Kowalik-Gęsiak Jolanta","schema":"Person","properties":{"name":["Kowalik-Gęsiak Jolanta"],"sourceUrl":["https://www.gov.pl/web/uw-mazowiecki/dyrektor-generalny"],"firstName":["Jolanta"],"lastName":["Kowalik-Gęsiak"],"topics":["role.pep"],"position":["Dyrektor Generalny Urzędu - mazowiecki"],"status":["Domestic Politically Exposed Person"]},"datasets":["pl_pep"]}
{"id":"pl-pep-lapicz-tomasz-1977-05-23","caption":"Łapicz Tomasz","schema":"Person","properties":{"name":["Łapicz Tomasz"],"sourceUrl":["https://bip.bydgoszcz.uw.gov.pl/24/dyrektor-generalny.html"],"firstName":["Tomasz"],"lastName":["Łapicz"],"birthDate":["1977-05-23"],"topics":["role.pep"],"position":["Dyrektor Generalny Urzędu - kujawsko-pomorski"],"status":["Domestic Politically Exposed Person"]},"datasets":["pl_pep"]}
{"id":"pl-pep-ostalecki-adam-1979-03-06","caption":"Ostalecki Adam","schema":"Person","properties":{"name":["Ostalecki Adam Stanisław"],"sourceUrl":["https://www.katowice.uw.gov.pl/strony/wojewoda/kierownictwo/dyrektor-generalny"],"firstName":["Adam"],"secondName":["Stanisław"],"lastName":["Ostalecki"],"birthDate":["1979-03-06"],"topics":["role.pep"],"position":["Dyrektor Generalny Urzędu - śląski"],"status":["Domestic Politically Exposed Person"]},"datasets":["pl_pep"]}
{"id":"pl-pep-sondej-roman-2xppdzlikedmz4d2sjqusjljpcy","caption":"Sondej Roman","schema":"Person","properties":{"name":["Sondej Roman"],"sourceUrl":["https://bip.lubuskie.uw.gov.pl/generalny/index"],"firstName":["Roman"],"lastName":["Sondej"],"topics":["role.pep"],"position":["Dyrektor Generalny Urzędu - lubuski"],"status":["Domestic Politically Exposed Person"]},"datasets":["pl_pep"]}
{"id":"pl-pep-spiker-andrzej-2xppe0uvdcurf7yvbksljzei5sa","caption":"Spiker Andrzej","schema":"Person","properties":{"name":["Spiker Andrzej"],"sourceUrl":["https://www.gdansk.uw.gov.pl/urzad/dyrektor-generalny"],"firstName":["Andrzej"],"lastName":["Spiker"],"topics":["role.pep"],"position":["Dyrektor Generalny Urzędu - pomorski"],"status":["Domestic Politically Exposed Person"]},"datasets":["pl_pep"]}
{"id":"pl-pep-srednicki-jaroslaw-1981-06-22","caption":"Średnicki Jarosław","schema":"Person","properties":{"name":["Średnicki Jarosław"],"sourceUrl":["https://www.gov.pl/web/uw-podlaski/dyrektor-generalny-jaroslaw-rednicki"],"firstName":["Jarosław"],"lastName":["Średnicki"],"birthDate":["1981-06-22"],"topics":["role.pep"],"position":["Dyrektor Generalny Urzędu - podlaski"],"status":["Domestic Politically Exposed Person"]},"datasets":["pl_pep"]}
{"id":"pl-pep-suski-miroslaw-2xppdxb1mipjvbxnca445jybqj5","caption":"Suski Mirosław","schema":"Person","properties":{"name":["Suski Mirosław"],"sourceUrl":["https://www.gov.pl/web/uw-lodzki/miroslaw-suski2"],"firstName":["Mirosław"],"lastName":["Suski"],"topics":["role.pep"],"position":["Dyrektor Generalny Urzędu - łódzki"],"status":["Domestic Politically Exposed Person"]},"datasets":["pl_pep"]}
{"id":"pl-pep-wozniak-jacek-1905-05-26","caption":"Woźniak Jacek","schema":"Person","properties":{"name":["Woźniak Jacek"],"sourceUrl":["https://www.poznan.uw.gov.pl/dyrektor-generalny"],"firstName":["Jacek"],"lastName":["Woźniak"],"birthDate":["1905-05-26"],"topics":["role.pep"],"position":["Dyrektor Generalny Urzędu - wielkopolski"],"status":["Domestic Politically Exposed Person"]},"datasets":["pl_pep"]}
{"id":"pl-pep-zaborniak-marcin-1905-05-24","caption":"Zaborniak Marcin","schema":"Person","properties":{"name":["Zaborniak Marcin"],"sourceUrl":["https://www.gov.pl/web/uw-podkarpacki/dyrektor-generalny"],"firstName":["Marcin"],"lastName":["Zaborniak"],"birthDate":["1905-05-24"],"topics":["role.pep"],"position":["Dyrektor Generalny Urzędu - podkarpacki"],"status":["Domestic Politically Exposed Person"]},"datasets":["pl_pep"]}
{"id":"pl-pep-zagorska-marta-2xppdykxjqgaowkrcbclauraylh","caption":"Zagórska Marta","schema":"Person","properties":{"name":["Zagórska Marta"],"sourceUrl":["https://www.szczecin.uw.gov.pl/?type=article\u0026action=view\u0026id=246"],"firstName":["Marta"],"lastName":["Zagórska"],"topics":["role.pep"],"position":["Dyrektor Generalny Urzędu - zachodniopomorski"],"status":["Domestic Politically Exposed Person"]},"datasets":["pl_pep"]}
{"id":"pl-pep-zukowski-pawel-1987-11-04","caption":"Żukowski Paweł","schema":"Person","properties":{"name":["Żukowski Paweł"],"sourceUrl":["https://www.gov.pl/web/uw-warminsko-mazurski/dyrektor-generalny"],"firstName":["Paweł"],"lastName":["Żukowski"],"birthDate":["1987-11-04"],"topics":["role.pep"],"position":["Dyrektor Generalny Urzędu - warmińsko-mazurski"],"status":["Domestic Politically Exposed Person"]},"datasets":["pl_pep"]}
{"id":"pl-pep-zwierzewicz-barbara-2xppdyobhmxampf1mpnxpowlvhw","caption":"Zwierzewicz Barbara","schema":"Person","properties":{"name":["Zwierzewicz Barbara"],"sourceUrl":["https://www.gov.pl/web/uw-opolski/dyrektor-generalny"],"firstName":["Barbara"],"lastName":["Zwierzewicz"],"topics":["role.pep"],"position":["Dyrektor Generalny Urzędu - opolski"],"status":["Domestic Politically Exposed Person"]},"datasets":["pl_pep"]}
